{"skeleton":{"hash":"pQqBtK42v0Y","spine":"4.0.64","x":-122.86,"y":-3.65,"width":265,"height":463,"images":"./images/","audio":"C:/Users/ACER/Desktop/New folder/green/images"},"bones":[{"name":"root"},{"name":"1","parent":"root","length":123.41,"rotation":90.37,"x":11.03,"y":175.76}],"slots":[{"name":"than","bone":"root","attachment":"than"},{"name":"1321","bone":"1","attachment":"1321"},{"name":"dau","bone":"1","attachment":"dau"},{"name":"2312","bone":"1","attachment":"2312"},{"name":"Shape 25","bone":"1","attachment":"Shape 25"},{"name":"Ellipse 1 copy 7","bone":"root"},{"name":"Ellipse 1 copy 2","bone":"1","attachment":"Ellipse 1 copy 2"},{"name":"Ellipse 1 copy 4","bone":"root"},{"name":"4","bone":"root"},{"name":"1411","bone":"root"},{"name":"9","bone":"1","attachment":"9"},{"name":"8","bone":"1","attachment":"8"},{"name":"7","bone":"1","attachment":"7"},{"name":"6","bone":"1","attachment":"6"},{"name":"21313245","bone":"1","attachment":"21313245"},{"name":"3","bone":"1","attachment":"3"},{"name":"4525","bone":"1","attachment":"4525"},{"name":"1","bone":"1","attachment":"1"},{"name":"mieng","bone":"1","attachment":"mieng"},{"name":"5","bone":"1","attachment":"5"},{"name":"Ellipse 1 copy 11","bone":"1","attachment":"Ellipse 1 copy 11"},{"name":"Ellipse 1 copy 10","bone":"1","attachment":"Ellipse 1 copy 10"},{"name":"4564326","bone":"1","attachment":"4564326"},{"name":"5645","bone":"1","attachment":"5645"},{"name":"2","bone":"1","attachment":"2"}],"skins":[{"name":"default","attachments":{"1":{"1":{"x":130.74,"y":23.05,"rotation":-90.37,"width":74,"height":134}},"2":{"2":{"x":241.67,"y":88.83,"rotation":-90.37,"width":61,"height":61}},"3":{"3":{"x":149.53,"y":-10.07,"rotation":-90.37,"width":20,"height":56}},"4":{"4":{"x":87,"y":-193,"width":86,"height":86}},"5":{"5":{"x":128.73,"y":-56.44,"rotation":-90.37,"width":81,"height":161}},"6":{"6":{"x":114.01,"y":65.16,"rotation":-90.37,"width":106,"height":180}},"7":{"7":{"x":132.51,"y":65.04,"rotation":-90.37,"width":106,"height":145}},"8":{"8":{"x":138.08,"y":76,"rotation":-90.37,"width":106,"height":132}},"9":{"9":{"x":195.6,"y":1.63,"rotation":-90.37,"width":66,"height":26}},"1321":{"1321":{"x":19.67,"y":12.77,"rotation":-90.37,"width":242,"height":136}},"1411":{"1411":{"x":182,"y":-173,"width":92,"height":46}},"2312":{"2312":{"x":90.28,"y":-48.69,"rotation":-90.37,"width":92,"height":86}},"4525":{"4525":{"x":123.19,"y":-61.9,"rotation":-90.37,"width":124,"height":150}},"5645":{"5645":{"x":241.16,"y":88.34,"rotation":-90.37,"width":86,"height":86}},"4564326":{"4564326":{"x":129.46,"y":56.56,"rotation":-90.37,"width":81,"height":161}},"21313245":{"21313245":{"x":110.92,"y":51.18,"rotation":-90.37,"width":102,"height":178}},"dau":{"dau":{"x":96.59,"y":-0.23,"rotation":-90.37,"width":215,"height":206}},"Ellipse 1 copy 2":{"Ellipse 1 copy 2":{"x":90.89,"y":46.31,"rotation":-90.37,"width":86,"height":86}},"Ellipse 1 copy 4":{"Ellipse 1 copy 4":{"x":87.5,"y":-193.5,"width":61,"height":61}},"Ellipse 1 copy 7":{"Ellipse 1 copy 7":{"x":179.5,"y":-193.5,"width":61,"height":61}},"Ellipse 1 copy 10":{"Ellipse 1 copy 10":{"x":240.51,"y":-90.16,"rotation":-90.37,"width":61,"height":61}},"Ellipse 1 copy 11":{"Ellipse 1 copy 11":{"x":240.01,"y":-89.66,"rotation":-90.37,"width":86,"height":86}},"mieng":{"mieng":{"x":31.1,"y":1.69,"rotation":-90.37,"width":48,"height":63}},"Shape 25":{"Shape 25":{"x":94.15,"y":86.29,"rotation":-90.37,"width":14,"height":10}},"than":{"than":{"x":11.14,"y":105.35,"width":148,"height":218}}}}],"animations":{"animation":{"bones":{"1":{"rotate":[{"value":20.79,"curve":"stepped"},{"time":0.1667,"value":0.96,"curve":"stepped"},{"time":0.3333,"value":20.79}],"translate":[{"x":21.45,"y":9.03,"curve":"stepped"},{"time":0.1667,"x":-15.81,"y":11.29,"curve":"stepped"},{"time":0.3333,"x":21.45,"y":9.03}],"scale":[{"x":1.2,"y":1.2,"curve":"stepped"},{"time":0.1667,"curve":"stepped"},{"time":0.3333,"x":1.2,"y":1.2}]}}}}}