{"skeleton":{"hash":"aUL0zOt0Wyo","spine":"4.0.64","x":-122.4,"y":-0.59,"width":246,"height":456.65,"images":"./images/","audio":""},"bones":[{"name":"root"},{"name":"DAU","parent":"root","length":104.77,"rotation":91.92,"x":-1.84,"y":178.59},{"name":"DAU2","parent":"DAU","x":97.61,"y":48.24},{"name":"2","parent":"DAU","x":96.27,"y":-44.2},{"name":"MIENG","parent":"DAU","x":28.81,"y":4}],"slots":[{"name":"than","bone":"root","attachment":"than"},{"name":"DAU","bone":"DAU","attachment":"DAU"},{"name":"MIENG","bone":"MIENG","attachment":"MIENG"},{"name":"1","bone":"DAU","attachment":"1"},{"name":"4","bone":"DAU","attachment":"1"},{"name":"2","bone":"2","attachment":"2"},{"name":"3","bone":"DAU2","attachment":"2"}],"skins":[{"name":"default","attachments":{"1":{"1":{"x":97.48,"y":-44.82,"scaleX":-1,"rotation":-91.92,"width":81,"height":81}},"2":{"2":{"x":-1.1,"y":-1.17,"scaleX":0.8,"scaleY":0.8,"rotation":-91.92,"width":61,"height":61}},"3":{"2":{"x":0.67,"y":-0.67,"rotation":-91.92,"width":61,"height":61}},"4":{"1":{"x":100.6,"y":48.11,"rotation":-91.92,"width":81,"height":81}},"DAU":{"DAU":{"x":134.31,"y":-6.95,"rotation":-91.92,"width":246,"height":286}},"MIENG":{"MIENG":{"x":0.24,"y":-2.08,"scaleX":0.3626,"rotation":-91.92,"width":100,"height":15}},"than":{"than":{"x":-0.66,"y":107.41,"width":106,"height":216}}}}],"animations":{"animation":{"bones":{"DAU":{"translate":[{"curve":"stepped"},{"time":0.3333,"y":2.57,"curve":"stepped"},{"time":0.5333,"y":6.17,"curve":"stepped"},{"time":0.8333,"y":8.74,"curve":"stepped"},{"time":0.9333,"y":-7.2,"curve":"stepped"},{"time":1.0333,"y":-0.51,"curve":"stepped"},{"time":1.3333}]},"DAU2":{"scale":[{"curve":"stepped"},{"time":0.3333,"x":0.418,"y":0.418,"curve":"stepped"},{"time":0.5667,"x":0.311,"y":0.311,"curve":"stepped"},{"time":0.9333,"x":1.147,"y":1.147,"curve":"stepped"},{"time":1.3333}]},"2":{"scale":[{"curve":"stepped"},{"time":0.3333,"x":0.418,"y":0.418,"curve":"stepped"},{"time":0.5667,"x":0.311,"y":0.311,"curve":"stepped"},{"time":0.9333,"x":1.147,"y":1.147,"curve":"stepped"},{"time":1.3333}]},"MIENG":{"scale":[{"curve":"stepped"},{"time":0.3333,"y":0.828,"curve":"stepped"},{"time":0.6,"y":0.757,"curve":"stepped"},{"time":0.9333,"y":2.563,"curve":"stepped"},{"time":1.0667,"y":2.038,"curve":"stepped"},{"time":1.3333}]}}}}}